CHANGELOG.md
LICENSE.txt
wagtail_sb_codefield/__init__.py
wagtail_sb_codefield/admin.py
wagtail_sb_codefield/apps.py
wagtail_sb_codefield/fields.py
wagtail_sb_codefield/migrations/__init__.py
wagtail_sb_codefield/models.py
wagtail_sb_codefield/static/wagtail_sb_codefield/css/codefield_wagtail_admin.css
wagtail_sb_codefield/templates/wagtail_sb_codefield/wagtail_tabbed_interface_script.html
wagtail_sb_codefield/tests.py
wagtail_sb_codefield/version.py
wagtail_sb_codefield/views.py
wagtail_sb_codefield/wagtail_hooks.py
wagtail_sb_codefield-0.4.0.dist-info/LICENSE.txt
wagtail_sb_codefield-0.4.0.dist-info/METADATA
wagtail_sb_codefield-0.4.0.dist-info/WHEEL
wagtail_sb_codefield-0.4.0.dist-info/RECORD
