Metadata-Version: 2.1
Name: wagtail-sb-codefield
Version: 0.4.0
Summary: Use CodeField from `django-sb-codefield` in Wagtail Admin
Home-page: https://gitlab.com/softbutterfly/open-source/wagtail-sb-codefield
License: MIT
Keywords: Softbutterfly,Django,Migrations
Author: SoftButterfly Development Team
Author-email: dev@softbutterfly.io
Requires-Python: >=3.8.1,<4.0.0
Classifier: Development Status :: 4 - Beta
Classifier: Environment :: Web Environment
Classifier: Intended Audience :: Developers
Classifier: License :: OSI Approved :: MIT License
Classifier: Natural Language :: English
Classifier: Programming Language :: Python :: 3
Classifier: Programming Language :: Python :: 3.9
Classifier: Programming Language :: Python :: 3.10
Classifier: Programming Language :: Python :: 3.11
Classifier: Programming Language :: Python :: 3.10
Classifier: Programming Language :: Python :: 3.8
Classifier: Programming Language :: Python :: 3.9
Classifier: Topic :: Software Development :: Libraries :: Python Modules
Requires-Dist: django (<5.0.0)
Requires-Dist: django-sb-codefield (<1.0.0)
Requires-Dist: wagtail (<6.0.0)
Project-URL: Bug Tracker, https://gitlab.com/softbutterfly/open-source/wagtail-sb-codefield/-/issues
Project-URL: Documentation, https://gitlab.com/softbutterfly/open-source/wagtail-sb-codefield/-/wikis
Project-URL: Download, https://gitlab.com/softbutterfly/open-source/wagtail-sb-codefield/-/archive/v0.4.0/wagtail-sb-codefield-v0.4.0.tar.gz
Project-URL: Repository, https://gitlab.com/softbutterfly/open-source/wagtail-sb-codefield
